bal_xilinx/__init__.py
bal_xilinx/context.py
bal_xilinx/data_model.py
bal_xilinx/defaults.py
bal_xilinx/format.py
bal_xilinx/analyzers/__init__.py
bal_xilinx/analyzers/device_analyzer.py
bal_xilinx/analyzers/encryption_analyzer.py
bal_xilinx/analyzers/visualizer_analyzer.py
bal_xilinx/configs/lx45t_fdri.json
bal_xilinx/configs/lx45t_fdri_logic_block.json
bal_xilinx/configs/lx9_fdri.json
bal_xilinx/configs/lx9_fdri_io_block.json
bal_xilinx/configs/lx9_fdri_logic_block.json
bal_xilinx/configs/xilinx_fdri_majors.json
bal_xilinx/configs/xilinx_registers.json
bal_xilinx/configs/xilinx_visualization.json
bal_xilinx/converters/__init__.py
bal_xilinx/converters/bitstream.py
bal_xilinx/converters/bitstream_packets.py
bal_xilinx/converters/bitstream_packets_1.py
bal_xilinx/converters/bitstream_packets_2.py
bal_xilinx/converters/bitstream_packets_fdri.py
bal_xilinx/modifiers/__init__.py
bal_xilinx/modifiers/pin_modifier.py
bal_xilinx/tools/__init__.py
bal_xilinx/tools/pin.py
bal_xilinx-0.1.dist-info/METADATA
bal_xilinx-0.1.dist-info/WHEEL
bal_xilinx-0.1.dist-info/top_level.txt
bal_xilinx-0.1.dist-info/RECORD
