Metadata-Version: 2.1
Name: bal-xilinx
Version: 0.1
Summary: An implementation of the BAL framework for Xilinx FPGAs
Home-page: UNKNOWN
Author: Red Balloon Security
Author-email: quack-tech@redballoonsecurity.com
License: UNKNOWN
Platform: UNKNOWN
Requires-Dist: bal
Requires-Dist: six
Requires-Dist: typing ; python_version < "3.5"
